cdktf_cdktf_provider_launchdarkly/__init__.py
cdktf_cdktf_provider_launchdarkly/py.typed
cdktf_cdktf_provider_launchdarkly/_jsii/__init__.py
cdktf_cdktf_provider_launchdarkly/_jsii/provider-launchdarkly@5.1.0.jsii.tgz
cdktf_cdktf_provider_launchdarkly/access_token/__init__.py
cdktf_cdktf_provider_launchdarkly/audit_log_subscription/__init__.py
cdktf_cdktf_provider_launchdarkly/custom_role/__init__.py
cdktf_cdktf_provider_launchdarkly/data_launchdarkly_audit_log_subscription/__init__.py
cdktf_cdktf_provider_launchdarkly/data_launchdarkly_environment/__init__.py
cdktf_cdktf_provider_launchdarkly/data_launchdarkly_feature_flag/__init__.py
cdktf_cdktf_provider_launchdarkly/data_launchdarkly_feature_flag_environment/__init__.py
cdktf_cdktf_provider_launchdarkly/data_launchdarkly_flag_trigger/__init__.py
cdktf_cdktf_provider_launchdarkly/data_launchdarkly_metric/__init__.py
cdktf_cdktf_provider_launchdarkly/data_launchdarkly_project/__init__.py
cdktf_cdktf_provider_launchdarkly/data_launchdarkly_relay_proxy_configuration/__init__.py
cdktf_cdktf_provider_launchdarkly/data_launchdarkly_segment/__init__.py
cdktf_cdktf_provider_launchdarkly/data_launchdarkly_team/__init__.py
cdktf_cdktf_provider_launchdarkly/data_launchdarkly_team_member/__init__.py
cdktf_cdktf_provider_launchdarkly/data_launchdarkly_team_members/__init__.py
cdktf_cdktf_provider_launchdarkly/data_launchdarkly_webhook/__init__.py
cdktf_cdktf_provider_launchdarkly/destination/__init__.py
cdktf_cdktf_provider_launchdarkly/environment/__init__.py
cdktf_cdktf_provider_launchdarkly/feature_flag/__init__.py
cdktf_cdktf_provider_launchdarkly/feature_flag_environment/__init__.py
cdktf_cdktf_provider_launchdarkly/flag_trigger/__init__.py
cdktf_cdktf_provider_launchdarkly/metric/__init__.py
cdktf_cdktf_provider_launchdarkly/project/__init__.py
cdktf_cdktf_provider_launchdarkly/provider/__init__.py
cdktf_cdktf_provider_launchdarkly/relay_proxy_configuration/__init__.py
cdktf_cdktf_provider_launchdarkly-5.1.0.dist-info/LICENSE
cdktf_cdktf_provider_launchdarkly-5.1.0.dist-info/METADATA
cdktf_cdktf_provider_launchdarkly-5.1.0.dist-info/WHEEL
cdktf_cdktf_provider_launchdarkly-5.1.0.dist-info/top_level.txt
cdktf_cdktf_provider_launchdarkly-5.1.0.dist-info/RECORD
